alphavantage_mcp_server/__init__.py
alphavantage_mcp_server/api.py
alphavantage_mcp_server/server.py
mseep_alphavantage-0.3.12.dist-info/METADATA
mseep_alphavantage-0.3.12.dist-info/WHEEL
mseep_alphavantage-0.3.12.dist-info/entry_points.txt
mseep_alphavantage-0.3.12.dist-info/licenses/LICENSE
mseep_alphavantage-0.3.12.dist-info/RECORD
