Metadata-Version: 2.4
Name: mseep-alphavantage
Version: 0.3.12
Summary: Alphavantage MCP server
Author-email: mseep <support@skydeck.ai>
Maintainer-email: mseep <support@skydeck.ai>
License-File: LICENSE
Requires-Python: >=3.12
Requires-Dist: bump2version>=1.0.1
Requires-Dist: load-dotenv>=0.1.0
Requires-Dist: mcp>=1.0.0
Requires-Dist: toml>=0.10.2
